krx300_hj3415/__init__.py
krx300_hj3415/__main__.py
krx300_hj3415/di.py
krx300_hj3415/adapters/__init__.py
krx300_hj3415/adapters/constants.py
krx300_hj3415/adapters/impls.py
krx300_hj3415/adapters/clients/__init__.py
krx300_hj3415/adapters/clients/http.py
krx300_hj3415/adapters/repos/__init__.py
krx300_hj3415/adapters/repos/hashutil.py
krx300_hj3415/adapters/repos/sqlite_repo.py
krx300_hj3415/adapters/repos/state_store.py
krx300_hj3415/adapters/services/__init__.py
krx300_hj3415/adapters/services/download.py
krx300_hj3415/adapters/services/excel.py
krx300_hj3415/core/__init__.py
krx300_hj3415/core/ports.py
krx300_hj3415/core/usecases/__init__.py
krx300_hj3415/core/usecases/sync_snapshot.py
krx300_hj3415/entrypoints/__init__.py
krx300_hj3415/entrypoints/cli.py
krx300_hj3415-1.0.4.dist-info/entry_points.txt
krx300_hj3415-1.0.4.dist-info/licenses/LICENSE
krx300_hj3415-1.0.4.dist-info/WHEEL
krx300_hj3415-1.0.4.dist-info/METADATA
krx300_hj3415-1.0.4.dist-info/RECORD
